[
  {
    "type": "paragraph_start"
  },
  {
    "sectionNumber": 1,
    "verseNumber": 1,
    "chapterNumber": null,
    "type": "paragraph_text",
    "value": "Then Jacob called for his sons and said: “Gather around so I can tell you what will happen to you in days to come."
  },
  {
    "type": "paragraph_end"
  },
  {
    "type": "stanza_start"
  },
  {
    "sectionNumber": 2,
    "verseNumber": 1,
    "chapterNumber": null,
    "type": "line_text",
    "value": ""
  },
  {
    "sectionNumber": 1,
    "verseNumber": 2,
    "chapterNumber": null,
    "type": "line_text",
    "value": "“Assemble and listen, sons of Jacob;"
  },
  {
    "type": "line_break"
  },
  {
    "sectionNumber": 2,
    "verseNumber": 2,
    "chapterNumber": null,
    "type": "line_text",
    "value": "listen to your father Israel."
  },
  {
    "type": "line_break"
  },
  {
    "type": "stanza_end"
  },
  {
    "type": "stanza_start"
  },
  {
    "sectionNumber": 3,
    "verseNumber": 2,
    "chapterNumber": null,
    "type": "line_text",
    "value": ""
  },
  {
    "sectionNumber": 1,
    "verseNumber": 3,
    "chapterNumber": null,
    "type": "line_text",
    "value": "“Reuben, you are my firstborn,"
  },
  {
    "type": "line_break"
  },
  {
    "sectionNumber": 2,
    "verseNumber": 3,
    "chapterNumber": null,
    "type": "line_text",
    "value": "my might, the first sign of my strength,"
  },
  {
    "type": "line_break"
  },
  {
    "sectionNumber": 3,
    "verseNumber": 3,
    "chapterNumber": null,
    "type": "line_text",
    "value": "excelling in honor, excelling in power."
  },
  {
    "type": "line_break"
  },
  {
    "sectionNumber": 1,
    "verseNumber": 4,
    "chapterNumber": null,
    "type": "line_text",
    "value": "Turbulent as the waters, you will no longer excel,"
  },
  {
    "type": "line_break"
  },
  {
    "sectionNumber": 2,
    "verseNumber": 4,
    "chapterNumber": null,
    "type": "line_text",
    "value": "for you went up onto your father’s bed,"
  },
  {
    "type": "line_break"
  },
  {
    "sectionNumber": 3,
    "verseNumber": 4,
    "chapterNumber": null,
    "type": "line_text",
    "value": "onto my couch and defiled it."
  },
  {
    "type": "line_break"
  },
  {
    "type": "stanza_end"
  },
  {
    "type": "stanza_start"
  },
  {
    "sectionNumber": 4,
    "verseNumber": 4,
    "chapterNumber": null,
    "type": "line_text",
    "value": ""
  },
  {
    "sectionNumber": 1,
    "verseNumber": 5,
    "chapterNumber": null,
    "type": "line_text",
    "value": "“Simeon and Levi are brothers—"
  },
  {
    "type": "line_break"
  },
  {
    "sectionNumber": 2,
    "verseNumber": 5,
    "chapterNumber": null,
    "type": "line_text",
    "value": "their swordsare weapons of violence."
  },
  {
    "type": "line_break"
  },
  {
    "sectionNumber": 1,
    "verseNumber": 6,
    "chapterNumber": null,
    "type": "line_text",
    "value": "Let me not enter their council,"
  },
  {
    "type": "line_break"
  },
  {
    "sectionNumber": 2,
    "verseNumber": 6,
    "chapterNumber": null,
    "type": "line_text",
    "value": "let me not join their assembly,"
  },
  {
    "type": "line_break"
  },
  {
    "sectionNumber": 3,
    "verseNumber": 6,
    "chapterNumber": null,
    "type": "line_text",
    "value": "for they have killed men in their anger"
  },
  {
    "type": "line_break"
  },
  {
    "sectionNumber": 4,
    "verseNumber": 6,
    "chapterNumber": null,
    "type": "line_text",
    "value": "and hamstrung oxen as they pleased."
  },
  {
    "type": "line_break"
  },
  {
    "sectionNumber": 1,
    "verseNumber": 7,
    "chapterNumber": null,
    "type": "line_text",
    "value": "Cursed be their anger, so fierce,"
  },
  {
    "type": "line_break"
  },
  {
    "sectionNumber": 2,
    "verseNumber": 7,
    "chapterNumber": null,
    "type": "line_text",
    "value": "and their fury, so cruel!"
  },
  {
    "type": "line_break"
  },
  {
    "sectionNumber": 3,
    "verseNumber": 7,
    "chapterNumber": null,
    "type": "line_text",
    "value": "I will scatter them in Jacob"
  },
  {
    "type": "line_break"
  },
  {
    "sectionNumber": 4,
    "verseNumber": 7,
    "chapterNumber": null,
    "type": "line_text",
    "value": "and disperse them in Israel."
  },
  {
    "type": "line_break"
  },
  {
    "type": "stanza_end"
  },
  {
    "type": "stanza_start"
  },
  {
    "sectionNumber": 5,
    "verseNumber": 7,
    "chapterNumber": null,
    "type": "line_text",
    "value": ""
  },
  {
    "sectionNumber": 1,
    "verseNumber": 8,
    "chapterNumber": null,
    "type": "line_text",
    "value": "“Judah,your brothers will praise you;"
  },
  {
    "type": "line_break"
  },
  {
    "sectionNumber": 2,
    "verseNumber": 8,
    "chapterNumber": null,
    "type": "line_text",
    "value": "your hand will be on the neck of your enemies;"
  },
  {
    "type": "line_break"
  },
  {
    "sectionNumber": 3,
    "verseNumber": 8,
    "chapterNumber": null,
    "type": "line_text",
    "value": "your father’s sons will bow down to you."
  },
  {
    "type": "line_break"
  },
  {
    "sectionNumber": 1,
    "verseNumber": 9,
    "chapterNumber": null,
    "type": "line_text",
    "value": "You are a lion’s cub, Judah;"
  },
  {
    "type": "line_break"
  },
  {
    "sectionNumber": 2,
    "verseNumber": 9,
    "chapterNumber": null,
    "type": "line_text",
    "value": "you return from the prey, my son."
  },
  {
    "type": "line_break"
  },
  {
    "sectionNumber": 3,
    "verseNumber": 9,
    "chapterNumber": null,
    "type": "line_text",
    "value": "Like a lion he crouches and lies down,"
  },
  {
    "type": "line_break"
  },
  {
    "sectionNumber": 4,
    "verseNumber": 9,
    "chapterNumber": null,
    "type": "line_text",
    "value": "like a lioness—who dares to rouse him?"
  },
  {
    "type": "line_break"
  },
  {
    "sectionNumber": 1,
    "verseNumber": 10,
    "chapterNumber": null,
    "type": "line_text",
    "value": "The scepter will not depart from Judah,"
  },
  {
    "type": "line_break"
  },
  {
    "sectionNumber": 2,
    "verseNumber": 10,
    "chapterNumber": null,
    "type": "line_text",
    "value": "nor the ruler’s staff from between his feet,"
  },
  {
    "type": "line_break"
  },
  {
    "sectionNumber": 3,
    "verseNumber": 10,
    "chapterNumber": null,
    "type": "line_text",
    "value": "until he to whom it belongsshall come"
  },
  {
    "type": "line_break"
  },
  {
    "sectionNumber": 4,
    "verseNumber": 10,
    "chapterNumber": null,
    "type": "line_text",
    "value": "and the obedience of the nations shall be his."
  },
  {
    "type": "line_break"
  },
  {
    "sectionNumber": 1,
    "verseNumber": 11,
    "chapterNumber": null,
    "type": "line_text",
    "value": "He will tether his donkey to a vine,"
  },
  {
    "type": "line_break"
  },
  {
    "sectionNumber": 2,
    "verseNumber": 11,
    "chapterNumber": null,
    "type": "line_text",
    "value": "his colt to the choicest branch;"
  },
  {
    "type": "line_break"
  },
  {
    "sectionNumber": 3,
    "verseNumber": 11,
    "chapterNumber": null,
    "type": "line_text",
    "value": "he will wash his garments in wine,"
  },
  {
    "type": "line_break"
  },
  {
    "sectionNumber": 4,
    "verseNumber": 11,
    "chapterNumber": null,
    "type": "line_text",
    "value": "his robes in the blood of grapes."
  },
  {
    "type": "line_break"
  },
  {
    "sectionNumber": 1,
    "verseNumber": 12,
    "chapterNumber": null,
    "type": "line_text",
    "value": "His eyes will be darker than wine,"
  },
  {
    "type": "line_break"
  },
  {
    "sectionNumber": 2,
    "verseNumber": 12,
    "chapterNumber": null,
    "type": "line_text",
    "value": "his teeth whiter than milk."
  },
  {
    "type": "line_break"
  },
  {
    "type": "stanza_end"
  },
  {
    "type": "stanza_start"
  },
  {
    "sectionNumber": 3,
    "verseNumber": 12,
    "chapterNumber": null,
    "type": "line_text",
    "value": ""
  },
  {
    "sectionNumber": 1,
    "verseNumber": 13,
    "chapterNumber": null,
    "type": "line_text",
    "value": "“Zebulun will live by the seashore"
  },
  {
    "type": "line_break"
  },
  {
    "sectionNumber": 2,
    "verseNumber": 13,
    "chapterNumber": null,
    "type": "line_text",
    "value": "and become a haven for ships;"
  },
  {
    "type": "line_break"
  },
  {
    "sectionNumber": 3,
    "verseNumber": 13,
    "chapterNumber": null,
    "type": "line_text",
    "value": "his border will extend toward Sidon."
  },
  {
    "type": "line_break"
  },
  {
    "type": "stanza_end"
  },
  {
    "type": "stanza_start"
  },
  {
    "sectionNumber": 4,
    "verseNumber": 13,
    "chapterNumber": null,
    "type": "line_text",
    "value": ""
  },
  {
    "sectionNumber": 1,
    "verseNumber": 14,
    "chapterNumber": null,
    "type": "line_text",
    "value": "“Issachar is a rawboneddonkey"
  },
  {
    "type": "line_break"
  },
  {
    "sectionNumber": 2,
    "verseNumber": 14,
    "chapterNumber": null,
    "type": "line_text",
    "value": "lying down among the sheep pens."
  },
  {
    "type": "line_break"
  },
  {
    "sectionNumber": 1,
    "verseNumber": 15,
    "chapterNumber": null,
    "type": "line_text",
    "value": "When he sees how good is his resting place"
  },
  {
    "type": "line_break"
  },
  {
    "sectionNumber": 2,
    "verseNumber": 15,
    "chapterNumber": null,
    "type": "line_text",
    "value": "and how pleasant is his land,"
  },
  {
    "type": "line_break"
  },
  {
    "sectionNumber": 3,
    "verseNumber": 15,
    "chapterNumber": null,
    "type": "line_text",
    "value": "he will bend his shoulder to the burden"
  },
  {
    "type": "line_break"
  },
  {
    "sectionNumber": 4,
    "verseNumber": 15,
    "chapterNumber": null,
    "type": "line_text",
    "value": "and submit to forced labor."
  },
  {
    "type": "line_break"
  },
  {
    "type": "stanza_end"
  },
  {
    "type": "stanza_start"
  },
  {
    "sectionNumber": 5,
    "verseNumber": 15,
    "chapterNumber": null,
    "type": "line_text",
    "value": ""
  },
  {
    "sectionNumber": 1,
    "verseNumber": 16,
    "chapterNumber": null,
    "type": "line_text",
    "value": "“Danwill provide justice for his people"
  },
  {
    "type": "line_break"
  },
  {
    "sectionNumber": 2,
    "verseNumber": 16,
    "chapterNumber": null,
    "type": "line_text",
    "value": "as one of the tribes of Israel."
  },
  {
    "type": "line_break"
  },
  {
    "sectionNumber": 1,
    "verseNumber": 17,
    "chapterNumber": null,
    "type": "line_text",
    "value": "Dan will be a snake by the roadside,"
  },
  {
    "type": "line_break"
  },
  {
    "sectionNumber": 2,
    "verseNumber": 17,
    "chapterNumber": null,
    "type": "line_text",
    "value": "a viper along the path,"
  },
  {
    "type": "line_break"
  },
  {
    "sectionNumber": 3,
    "verseNumber": 17,
    "chapterNumber": null,
    "type": "line_text",
    "value": "that bites the horse’s heels"
  },
  {
    "type": "line_break"
  },
  {
    "sectionNumber": 4,
    "verseNumber": 17,
    "chapterNumber": null,
    "type": "line_text",
    "value": "so that its rider tumbles backward."
  },
  {
    "type": "line_break"
  },
  {
    "type": "stanza_end"
  },
  {
    "type": "stanza_start"
  },
  {
    "sectionNumber": 5,
    "verseNumber": 17,
    "chapterNumber": null,
    "type": "line_text",
    "value": ""
  },
  {
    "sectionNumber": 1,
    "verseNumber": 18,
    "chapterNumber": null,
    "type": "line_text",
    "value": "“I look for your deliverance,."
  },
  {
    "type": "line_break"
  },
  {
    "type": "stanza_end"
  },
  {
    "type": "stanza_start"
  },
  {
    "sectionNumber": 2,
    "verseNumber": 18,
    "chapterNumber": null,
    "type": "line_text",
    "value": ""
  },
  {
    "sectionNumber": 1,
    "verseNumber": 19,
    "chapterNumber": null,
    "type": "line_text",
    "value": "“Gadwill be attacked by a band of raiders,"
  },
  {
    "type": "line_break"
  },
  {
    "sectionNumber": 2,
    "verseNumber": 19,
    "chapterNumber": null,
    "type": "line_text",
    "value": "but he will attack them at their heels."
  },
  {
    "type": "line_break"
  },
  {
    "type": "stanza_end"
  },
  {
    "type": "stanza_start"
  },
  {
    "sectionNumber": 3,
    "verseNumber": 19,
    "chapterNumber": null,
    "type": "line_text",
    "value": ""
  },
  {
    "sectionNumber": 1,
    "verseNumber": 20,
    "chapterNumber": null,
    "type": "line_text",
    "value": "“Asher’s food will be rich;"
  },
  {
    "type": "line_break"
  },
  {
    "sectionNumber": 2,
    "verseNumber": 20,
    "chapterNumber": null,
    "type": "line_text",
    "value": "he will provide delicacies fit for a king."
  },
  {
    "type": "line_break"
  },
  {
    "type": "stanza_end"
  },
  {
    "type": "stanza_start"
  },
  {
    "sectionNumber": 3,
    "verseNumber": 20,
    "chapterNumber": null,
    "type": "line_text",
    "value": ""
  },
  {
    "sectionNumber": 1,
    "verseNumber": 21,
    "chapterNumber": null,
    "type": "line_text",
    "value": "“Naphtali is a doe set free"
  },
  {
    "type": "line_break"
  },
  {
    "sectionNumber": 2,
    "verseNumber": 21,
    "chapterNumber": null,
    "type": "line_text",
    "value": "that bears beautiful fawns."
  },
  {
    "type": "line_break"
  },
  {
    "type": "stanza_end"
  },
  {
    "type": "stanza_start"
  },
  {
    "sectionNumber": 3,
    "verseNumber": 21,
    "chapterNumber": null,
    "type": "line_text",
    "value": ""
  },
  {
    "sectionNumber": 1,
    "verseNumber": 22,
    "chapterNumber": null,
    "type": "line_text",
    "value": "“Joseph is a fruitful vine,"
  },
  {
    "type": "line_break"
  },
  {
    "sectionNumber": 2,
    "verseNumber": 22,
    "chapterNumber": null,
    "type": "line_text",
    "value": "a fruitful vine near a spring,"
  },
  {
    "type": "line_break"
  },
  {
    "sectionNumber": 3,
    "verseNumber": 22,
    "chapterNumber": null,
    "type": "line_text",
    "value": "whose branches climb over a wall."
  },
  {
    "type": "line_break"
  },
  {
    "sectionNumber": 1,
    "verseNumber": 23,
    "chapterNumber": null,
    "type": "line_text",
    "value": "With bitterness archers attacked him;"
  },
  {
    "type": "line_break"
  },
  {
    "sectionNumber": 2,
    "verseNumber": 23,
    "chapterNumber": null,
    "type": "line_text",
    "value": "they shot at him with hostility."
  },
  {
    "type": "line_break"
  },
  {
    "sectionNumber": 1,
    "verseNumber": 24,
    "chapterNumber": null,
    "type": "line_text",
    "value": "But his bow remained steady,"
  },
  {
    "type": "line_break"
  },
  {
    "sectionNumber": 2,
    "verseNumber": 24,
    "chapterNumber": null,
    "type": "line_text",
    "value": "his strong arms stayedlimber,"
  },
  {
    "type": "line_break"
  },
  {
    "sectionNumber": 3,
    "verseNumber": 24,
    "chapterNumber": null,
    "type": "line_text",
    "value": "because of the hand of the Mighty One of Jacob,"
  },
  {
    "type": "line_break"
  },
  {
    "sectionNumber": 4,
    "verseNumber": 24,
    "chapterNumber": null,
    "type": "line_text",
    "value": "because of the Shepherd, the Rock of Israel,"
  },
  {
    "type": "line_break"
  },
  {
    "sectionNumber": 1,
    "verseNumber": 25,
    "chapterNumber": null,
    "type": "line_text",
    "value": "because of your father’s God, who helps you,"
  },
  {
    "type": "line_break"
  },
  {
    "sectionNumber": 2,
    "verseNumber": 25,
    "chapterNumber": null,
    "type": "line_text",
    "value": "because of the Almighty,who blesses you"
  },
  {
    "type": "line_break"
  },
  {
    "sectionNumber": 3,
    "verseNumber": 25,
    "chapterNumber": null,
    "type": "line_text",
    "value": "with blessings of the skies above,"
  },
  {
    "type": "line_break"
  },
  {
    "sectionNumber": 4,
    "verseNumber": 25,
    "chapterNumber": null,
    "type": "line_text",
    "value": "blessings of the deep springs below,"
  },
  {
    "type": "line_break"
  },
  {
    "sectionNumber": 5,
    "verseNumber": 25,
    "chapterNumber": null,
    "type": "line_text",
    "value": "blessings of the breast and womb."
  },
  {
    "type": "line_break"
  },
  {
    "sectionNumber": 1,
    "verseNumber": 26,
    "chapterNumber": null,
    "type": "line_text",
    "value": "Your father’s blessings are greater"
  },
  {
    "type": "line_break"
  },
  {
    "sectionNumber": 2,
    "verseNumber": 26,
    "chapterNumber": null,
    "type": "line_text",
    "value": "than the blessings of the ancient mountains,"
  },
  {
    "type": "line_break"
  },
  {
    "sectionNumber": 3,
    "verseNumber": 26,
    "chapterNumber": null,
    "type": "line_text",
    "value": "thanthe bounty of the age-old hills."
  },
  {
    "type": "line_break"
  },
  {
    "sectionNumber": 4,
    "verseNumber": 26,
    "chapterNumber": null,
    "type": "line_text",
    "value": "Let all these rest on the head of Joseph,"
  },
  {
    "type": "line_break"
  },
  {
    "sectionNumber": 5,
    "verseNumber": 26,
    "chapterNumber": null,
    "type": "line_text",
    "value": "on the brow of the prince amonghis brothers."
  },
  {
    "type": "line_break"
  },
  {
    "type": "stanza_end"
  },
  {
    "type": "stanza_start"
  },
  {
    "sectionNumber": 6,
    "verseNumber": 26,
    "chapterNumber": null,
    "type": "line_text",
    "value": ""
  },
  {
    "sectionNumber": 1,
    "verseNumber": 27,
    "chapterNumber": null,
    "type": "line_text",
    "value": "“Benjamin is a ravenous wolf;"
  },
  {
    "type": "line_break"
  },
  {
    "sectionNumber": 2,
    "verseNumber": 27,
    "chapterNumber": null,
    "type": "line_text",
    "value": "in the morning he devours the prey,"
  },
  {
    "type": "line_break"
  },
  {
    "sectionNumber": 3,
    "verseNumber": 27,
    "chapterNumber": null,
    "type": "line_text",
    "value": "in the evening he divides the plunder.”"
  },
  {
    "type": "line_break"
  },
  {
    "type": "stanza_end"
  },
  {
    "type": "paragraph_start"
  },
  {
    "sectionNumber": 1,
    "verseNumber": 28,
    "chapterNumber": null,
    "type": "paragraph_text",
    "value": "All these are the twelve tribes of Israel, and this is what their father said to them when he blessed them, giving each the blessing appropriate to him."
  },
  {
    "type": "paragraph_end"
  },
  {
    "type": "paragraph_start"
  },
  {
    "sectionNumber": 1,
    "verseNumber": 29,
    "chapterNumber": null,
    "type": "paragraph_text",
    "value": "Then he gave them these instructions: “I am about to be gathered to my people. Bury me with my fathers in the cave in the field of Ephron the Hittite,"
  },
  {
    "sectionNumber": 1,
    "verseNumber": 30,
    "chapterNumber": null,
    "type": "paragraph_text",
    "value": "the cave in the field of Machpelah, near Mamre in Canaan, which Abraham bought along with the field as a burial place from Ephron the Hittite."
  },
  {
    "sectionNumber": 1,
    "verseNumber": 31,
    "chapterNumber": null,
    "type": "paragraph_text",
    "value": "There Abraham and his wife Sarah were buried, there Isaac and his wife Rebekah were buried, and there I buried Leah."
  },
  {
    "sectionNumber": 1,
    "verseNumber": 32,
    "chapterNumber": null,
    "type": "paragraph_text",
    "value": "The field and the cave in it were bought from the Hittites.”"
  },
  {
    "type": "paragraph_end"
  },
  {
    "type": "paragraph_start"
  },
  {
    "sectionNumber": 1,
    "verseNumber": 33,
    "chapterNumber": null,
    "type": "paragraph_text",
    "value": "When Jacob had finished giving instructions to his sons, he drew his feet up into the bed, breathed his last and was gathered to his people."
  },
  {
    "type": "paragraph_end"
  }
]